GooglePictureCrawlerWithSQS-2.0.7.dist-info/DESCRIPTION.rst
GooglePictureCrawlerWithSQS-2.0.7.dist-info/METADATA
GooglePictureCrawlerWithSQS-2.0.7.dist-info/RECORD
GooglePictureCrawlerWithSQS-2.0.7.dist-info/WHEEL
GooglePictureCrawlerWithSQS-2.0.7.dist-info/metadata.json
GooglePictureCrawlerWithSQS-2.0.7.dist-info/top_level.txt
PictureCrawler/__init__.py
PictureCrawler/API/APICrawlerManager.py
PictureCrawler/API/APIStarter.py
PictureCrawler/API/__init__.py
PictureCrawler/crawler/__init__.py
PictureCrawler/crawler/Constants/AWSConstants.py
PictureCrawler/crawler/Constants/CrawlerConstants.py
PictureCrawler/crawler/Constants/__init__.py
PictureCrawler/crawler/Crawler/Crawler.py
PictureCrawler/crawler/Crawler/CrawlerExecuter.py
PictureCrawler/crawler/Crawler/CrawlerManagerBing.py
PictureCrawler/crawler/Crawler/CrawlerManagerGoogle.py
PictureCrawler/crawler/Crawler/CrwalerFactory.py
PictureCrawler/crawler/Crawler/__init__.py
PictureCrawler/crawler/Managers/SQSManager.py
PictureCrawler/crawler/Managers/__init__.py
