Metadata-Version: 2.0
Name: GooglePictureCrawlerWithSQS
Version: 2.0.7
Summary: Google picture crawler with SQS connection
Home-page: UNKNOWN
Author: Florian Muchow
Author-email: flmuchow@gmail.com
License: UNKNOWN
Keywords: setuptools development AWS sqs google crawler pictures googlepictures
Platform: UNKNOWN
Classifier: Development Status :: 5 - Production/Stable
Classifier: Intended Audience :: Developers
Classifier: Topic :: Software Development :: Build Tools
Classifier: License :: OSI Approved :: MIT License
Classifier: Programming Language :: Python :: 3.6
Requires-Dist: setuptools
Requires-Dist: bs4
Requires-Dist: boto3
Requires-Dist: urllib3
Requires-Dist: request
Requires-Dist: requests
Requires-Dist: flask
Requires-Dist: flask-restful-url-generator
